[{"hno":261,"hnm":"현대,우성","typeNm":"아파트","callPrice":"3354.25","realPrice":"2757.97","kbPrice":3133.62,"call_KB":"107.04","real_KB":"88.01","callCount":17,"realCount":5,"naver_link":"https://new.land.naver.com/complexes/261"},{"hno":263,"hnm":"한신","typeNm":"아파트","callPrice":"3060.48","realPrice":"2755.80","kbPrice":2982.26,"call_KB":"102.62","real_KB":"92.40","callCount":62,"realCount":21,"naver_link":"https://new.land.naver.com/complexes/263"},{"hno":25841,"hnm":"청구(284)","typeNm":"아파트","callPrice":"2894.33","realPrice":"2657.20","kbPrice":2792.05,"call_KB":"103.66","real_KB":"95.17","callCount":23,"realCount":4,"naver_link":"https://new.land.naver.com/complexes/25841"},{"hno":1118,"hnm":"하계현대","typeNm":"아파트","callPrice":"2857.74","realPrice":"2576.61","kbPrice":2797.45,"call_KB":"102.15","real_KB":"92.10","callCount":27,"realCount":6,"naver_link":"https://new.land.naver.com/complexes/1118"},{"hno":255,"hnm":"극동.건영.벽산","typeNm":"아파트","callPrice":"2775.39","realPrice":"2614.66","kbPrice":2770.39,"call_KB":"100.18","real_KB":"94.37","callCount":62,"realCount":22,"naver_link":"https://new.land.naver.com/complexes/255"},{"hno":257,"hnm":"미성","typeNm":"아파트","callPrice":"2774.19","realPrice":"2639.95","kbPrice":2696.11,"call_KB":"102.89","real_KB":"97.91","callCount":26,"realCount":3,"naver_link":"https://new.land.naver.com/complexes/257"},{"hno":3257,"hnm":"하계1차청구","typeNm":"아파트","callPrice":"2716.85","realPrice":"2545.59","kbPrice":2600.08,"call_KB":"104.49","real_KB":"97.90","callCount":10,"realCount":8,"naver_link":"https://new.land.naver.com/complexes/3257"},{"hno":1117,"hnm":"한신동성","typeNm":"아파트","callPrice":"2525.92","realPrice":"1805.88","kbPrice":2537.72,"call_KB":"99.53","real_KB":"71.16","callCount":22,"realCount":2,"naver_link":"https://new.land.naver.com/complexes/1117"},{"hno":126,"hnm":"청솔","typeNm":"아파트","callPrice":"2466.33","realPrice":"2181.71","kbPrice":2294.28,"call_KB":"107.49","real_KB":"95.09","callCount":62,"realCount":15,"naver_link":"https://new.land.naver.com/complexes/126"},{"hno":128,"hnm":"학여울청구","typeNm":"아파트","callPrice":"2447.36","realPrice":"2265.10","kbPrice":2358.11,"call_KB":"103.78","real_KB":"96.05","callCount":55,"realCount":17,"naver_link":"https://new.land.naver.com/complexes/128"},{"hno":260,"hnm":"삼익선경","typeNm":"아파트","callPrice":"2396.88","realPrice":"2292.90","kbPrice":2234.49,"call_KB":"107.26","real_KB":"102.61","callCount":20,"realCount":1,"naver_link":"https://new.land.naver.com/complexes/260"},{"hno":262,"hnm":"장미","typeNm":"아파트","callPrice":"2124.13","realPrice":"2474.11","kbPrice":2729.5,"call_KB":"77.82","real_KB":"90.64","callCount":31,"realCount":22,"naver_link":"https://new.land.naver.com/complexes/262"},{"hno":1270,"hnm":"하계우방","typeNm":"아파트","callPrice":"2040.76","realPrice":"1974.22","kbPrice":2003.13,"call_KB":"101.87","real_KB":"98.55","callCount":12,"realCount":1,"naver_link":"https://new.land.naver.com/complexes/1270"},{"hno":13214,"hnm":"하계청구(279)","typeNm":"아파트","callPrice":"1889.13","realPrice":"없음","kbPrice":1678.3,"call_KB":"112.56","real_KB":"없음","callCount":6,"realCount":0,"naver_link":"https://new.land.naver.com/complexes/13214"}]