[{"hno":133610,"hnm":"운서2차SK뷰스카이시티","typeNm":"아파트","callPrice":"1460.08","realPrice":"없음","kbPrice":1241.86,"call_KB":"117.57","real_KB":"없음","callCount":8,"realCount":0,"naver_link":"https://new.land.naver.com/complexes/133610"},{"hno":114163,"hnm":"e편한세상영종하늘도시","typeNm":"아파트","callPrice":"1390.77","realPrice":"1318.22","kbPrice":1399.9,"call_KB":"99.34","real_KB":"94.16","callCount":54,"realCount":12,"naver_link":"https://new.land.naver.com/complexes/114163"},{"hno":115691,"hnm":"영종센트럴푸르지오자이","typeNm":"아파트","callPrice":"1276.02","realPrice":"1253.46","kbPrice":1330.38,"call_KB":"95.91","real_KB":"94.21","callCount":66,"realCount":55,"naver_link":"https://new.land.naver.com/complexes/115691"},{"hno":27689,"hnm":"영종자이","typeNm":"아파트","callPrice":"1078.31","realPrice":"962.37","kbPrice":1028.07,"call_KB":"104.88","real_KB":"93.60","callCount":80,"realCount":16,"naver_link":"https://new.land.naver.com/complexes/27689"}]