[{"hno":6781,"hnm":"새뜸현대","typeNm":"아파트","callPrice":"683.74","realPrice":"762.64","kbPrice":834.3,"call_KB":"81.95","real_KB":"91.41","callCount":19,"realCount":10,"naver_link":"https://new.land.naver.com/complexes/6781"},{"hno":104513,"hnm":"공주신금우남퍼스트빌","typeNm":"아파트","callPrice":"653.64","realPrice":"890.47","kbPrice":906.77,"call_KB":"72.08","real_KB":"98.20","callCount":9,"realCount":23,"naver_link":"https://new.land.naver.com/complexes/104513"},{"hno":115418,"hnm":"공주월송흥화하브","typeNm":"아파트","callPrice":"1105.16","realPrice":"1020.88","kbPrice":999.23,"call_KB":"110.60","real_KB":"102.16","callCount":36,"realCount":11,"naver_link":"https://new.land.naver.com/complexes/115418"}]