[{"hno":119927,"hnm":"익산동산제일오투그란데","typeNm":"아파트","callPrice":"967.37","realPrice":"919.76","kbPrice":952.73,"call_KB":"101.53","real_KB":"96.53","callCount":38,"realCount":11,"naver_link":"https://new.land.naver.com/complexes/119927"},{"hno":118923,"hnm":"익산수도산코아루이지움","typeNm":"아파트","callPrice":"830.63","realPrice":"811.37","kbPrice":876.69,"call_KB":"94.74","real_KB":"92.55","callCount":27,"realCount":4,"naver_link":"https://new.land.naver.com/complexes/118923"},{"hno":101779,"hnm":"동산제일2차","typeNm":"아파트","callPrice":"564.32","realPrice":"499.10","kbPrice":530.48,"call_KB":"106.37","real_KB":"94.08","callCount":14,"realCount":7,"naver_link":"https://new.land.naver.com/complexes/101779"},{"hno":5125,"hnm":"삼호1차","typeNm":"아파트","callPrice":"476.05","realPrice":"404.42","kbPrice":421.43,"call_KB":"112.96","real_KB":"95.96","callCount":4,"realCount":1,"naver_link":"https://new.land.naver.com/complexes/5125"},{"hno":5129,"hnm":"우성","typeNm":"아파트","callPrice":"423.63","realPrice":"415.43","kbPrice":413.06,"call_KB":"102.55","real_KB":"100.57","callCount":13,"realCount":10,"naver_link":"https://new.land.naver.com/complexes/5129"},{"hno":8597,"hnm":"세경","typeNm":"재건축","callPrice":"415.23","realPrice":"284.57","kbPrice":554.49,"call_KB":"74.88","real_KB":"51.32","callCount":40,"realCount":9,"naver_link":"https://new.land.naver.com/complexes/8597"},{"hno":5124,"hnm":"삼성","typeNm":"아파트","callPrice":"412.55","realPrice":"366.31","kbPrice":401.65,"call_KB":"102.71","real_KB":"91.20","callCount":6,"realCount":3,"naver_link":"https://new.land.naver.com/complexes/5124"},{"hno":5123,"hnm":"비사벌","typeNm":"아파트","callPrice":"411.86","realPrice":"368.09","kbPrice":415.65,"call_KB":"99.08","real_KB":"88.55","callCount":12,"realCount":2,"naver_link":"https://new.land.naver.com/complexes/5123"},{"hno":112930,"hnm":"오씨아이사원","typeNm":"아파트","callPrice":"401.12","realPrice":"363.26","kbPrice":423.86,"call_KB":"94.63","real_KB":"85.70","callCount":13,"realCount":2,"naver_link":"https://new.land.naver.com/complexes/112930"},{"hno":14999,"hnm":"우남","typeNm":"아파트","callPrice":"378.74","realPrice":"370.01","kbPrice":371.46,"call_KB":"101.95","real_KB":"99.60","callCount":11,"realCount":8,"naver_link":"https://new.land.naver.com/complexes/14999"},{"hno":101789,"hnm":"그린팰리스","typeNm":"아파트","callPrice":"338.00","realPrice":"640.05","kbPrice":675.86,"call_KB":"50.01","real_KB":"94.70","callCount":20,"realCount":6,"naver_link":"https://new.land.naver.com/complexes/101789"},{"hno":5134,"hnm":"한성","typeNm":"아파트","callPrice":"309.76","realPrice":"278.28","kbPrice":282.68,"call_KB":"109.58","real_KB":"98.44","callCount":4,"realCount":3,"naver_link":"https://new.land.naver.com/complexes/5134"},{"hno":5121,"hnm":"동신","typeNm":"아파트","callPrice":"266.22","realPrice":"310.29","kbPrice":311.53,"call_KB":"85.45","real_KB":"99.59","callCount":15,"realCount":10,"naver_link":"https://new.land.naver.com/complexes/5121"},{"hno":5126,"hnm":"삼호2차","typeNm":"아파트","callPrice":"223.20","realPrice":"409.98","kbPrice":419.06,"call_KB":"53.26","real_KB":"97.83","callCount":4,"realCount":2,"naver_link":"https://new.land.naver.com/complexes/5126"},{"hno":101161,"hnm":"동산라인","typeNm":"아파트","callPrice":"205.80","realPrice":"365.02","kbPrice":393.31,"call_KB":"52.32","real_KB":"92.80","callCount":2,"realCount":13,"naver_link":"https://new.land.naver.com/complexes/101161"},{"hno":5128,"hnm":"우남남부","typeNm":"아파트","callPrice":"186.14","realPrice":"179.61","kbPrice":332.99,"call_KB":"55.90","real_KB":"53.93","callCount":1,"realCount":3,"naver_link":"https://new.land.naver.com/complexes/5128"},{"hno":5131,"hnm":"제일","typeNm":"아파트","callPrice":"174.55","realPrice":"369.97","kbPrice":368.34,"call_KB":"47.38","real_KB":"100.44","callCount":6,"realCount":4,"naver_link":"https://new.land.naver.com/complexes/5131"}]