[{"hno":3832,"hnm":"중림삼성사이버빌리지","typeNm":"아파트","callPrice":4336.7,"realPrice":4007.61,"kbPrice":4141.06,"call_KB":104.72,"real_KB":96.77,"callCount":14,"realCount":7},{"hno":13721,"hnm":"브라운스톤서울(주상복합)","typeNm":"아파트","callPrice":4011.28,"realPrice":3379.84,"kbPrice":3153.21,"call_KB":127.21,"real_KB":107.18,"callCount":7,"realCount":3},{"hno":21937,"hnm":"브라운스톤서울","typeNm":"오피스텔","callPrice":1890.49,"realPrice":1453.75,"kbPrice":1784.32,"call_KB":105.95,"real_KB":81.47,"callCount":15,"realCount":3}]