[{"hno":13813,"hnm":"역삼e-편한세상","typeNm":"아파트","callPrice":8554.24,"realPrice":7800.7,"kbPrice":7894.16,"call_KB":108.36,"real_KB":98.81,"callCount":41,"realCount":15},{"hno":14142,"hnm":"역삼푸르지오","typeNm":"아파트","callPrice":8230.16,"realPrice":7575.48,"kbPrice":7834.21,"call_KB":105.05,"real_KB":96.69,"callCount":27,"realCount":13},{"hno":103376,"hnm":"개나리SK뷰","typeNm":"아파트","callPrice":8121.15,"realPrice":7876.26,"kbPrice":7755.72,"call_KB":104.71,"real_KB":101.55,"callCount":15,"realCount":2},{"hno":104032,"hnm":"테헤란아이파크","typeNm":"아파트","callPrice":7949.88,"realPrice":7395.12,"kbPrice":8015.22,"call_KB":99.18,"real_KB":92.26,"callCount":38,"realCount":7},{"hno":837,"hnm":"래미안그레이튼2차","typeNm":"아파트","callPrice":7836.72,"realPrice":7870.7,"kbPrice":6840.1,"call_KB":114.57,"real_KB":115.06,"callCount":18,"realCount":1},{"hno":13814,"hnm":"역삼래미안","typeNm":"아파트","callPrice":7771.1,"realPrice":7333.84,"kbPrice":7465.4,"call_KB":104.09,"real_KB":98.23,"callCount":48,"realCount":21},{"hno":588,"hnm":"동부센트레빌","typeNm":"아파트","callPrice":7691.62,"realPrice":5470.14,"kbPrice":6866.31,"call_KB":112.01,"real_KB":79.66,"callCount":15,"realCount":3},{"hno":17528,"hnm":"개나리푸르지오","typeNm":"아파트","callPrice":7606.69,"realPrice":7994.44,"kbPrice":7020.71,"call_KB":108.34,"real_KB":113.86,"callCount":23,"realCount":3},{"hno":394,"hnm":"래미안그레이튼3차","typeNm":"아파트","callPrice":7545.22,"realPrice":7238.39,"kbPrice":6782.65,"call_KB":111.24,"real_KB":106.71,"callCount":31,"realCount":6},{"hno":109227,"hnm":"역삼자이","typeNm":"아파트","callPrice":7331.05,"realPrice":7118.82,"kbPrice":7510.7,"call_KB":97.6,"real_KB":94.78,"callCount":43,"realCount":3},{"hno":18213,"hnm":"개나리래미안","typeNm":"아파트","callPrice":7292.98,"realPrice":6946.14,"kbPrice":7172.98,"call_KB":101.67,"real_KB":96.83,"callCount":23,"realCount":7},{"hno":24081,"hnm":"역삼2차아이파크","typeNm":"아파트","callPrice":7254.07,"realPrice":6664.08,"kbPrice":6760.53,"call_KB":107.3,"real_KB":98.57,"callCount":9,"realCount":3},{"hno":17805,"hnm":"역삼IPARK","typeNm":"아파트","callPrice":6929.35,"realPrice":7023.08,"kbPrice":6146.13,"call_KB":112.74,"real_KB":114.26,"callCount":40,"realCount":2},{"hno":22386,"hnm":"래미안펜타빌","typeNm":"아파트","callPrice":6822.68,"realPrice":6539.3,"kbPrice":6397.36,"call_KB":106.64,"real_KB":102.21,"callCount":27,"realCount":4},{"hno":977,"hnm":"대림역삼","typeNm":"아파트","callPrice":6079.83,"realPrice":5890.7,"kbPrice":5691.09,"call_KB":106.83,"real_KB":103.5,"callCount":7,"realCount":1},{"hno":11429,"hnm":"세방하이빌","typeNm":"아파트","callPrice":5960.49,"realPrice":null,"kbPrice":4846.99,"call_KB":122.97,"real_KB":null,"callCount":2,"realCount":0},{"hno":3316,"hnm":"현대까르띠에710","typeNm":"아파트","callPrice":5795.06,"realPrice":5545.21,"kbPrice":4840.13,"call_KB":119.72,"real_KB":114.56,"callCount":6,"realCount":1},{"hno":18991,"hnm":"쌍용플래티넘밸류(주상복합)","typeNm":"아파트","callPrice":5429.67,"realPrice":null,"kbPrice":3932.82,"call_KB":138.06,"real_KB":null,"callCount":7,"realCount":0},{"hno":17527,"hnm":"역삼월드메르디앙","typeNm":"아파트","callPrice":5339.09,"realPrice":null,"kbPrice":4415.04,"call_KB":120.92,"real_KB":null,"callCount":3,"realCount":0},{"hno":9123,"hnm":"금호어울림","typeNm":"아파트","callPrice":5037.15,"realPrice":5164.62,"kbPrice":4479.97,"call_KB":112.43,"real_KB":115.28,"callCount":13,"realCount":1},{"hno":17795,"hnm":"역삼우정에쉐르2(주상복합)","typeNm":"아파트","callPrice":4796.46,"realPrice":3464.94,"kbPrice":4205.47,"call_KB":114.05,"real_KB":82.39,"callCount":3,"realCount":1},{"hno":3314,"hnm":"경남","typeNm":"아파트","callPrice":4719.78,"realPrice":4458.7,"kbPrice":4669.04,"call_KB":101.08,"real_KB":95.49,"callCount":11,"realCount":1},{"hno":22320,"hnm":"역삼롯데캐슬노블","typeNm":"아파트","callPrice":4514.33,"realPrice":null,"kbPrice":3417.91,"call_KB":132.07,"real_KB":null,"callCount":8,"realCount":0},{"hno":14295,"hnm":"역삼우정에쉐르1(주상복합)","typeNm":"아파트","callPrice":3982.62,"realPrice":null,"kbPrice":3646.32,"call_KB":109.22,"real_KB":null,"callCount":5,"realCount":0},{"hno":102310,"hnm":"강남서해그랑블(주상복합)","typeNm":"아파트","callPrice":3675.07,"realPrice":null,"kbPrice":3729.93,"call_KB":98.52,"real_KB":null,"callCount":8,"realCount":0},{"hno":3315,"hnm":"디오빌역삼(주상복합)","typeNm":"아파트","callPrice":3470.3,"realPrice":2869.09,"kbPrice":3036.55,"call_KB":114.28,"real_KB":94.48,"callCount":31,"realCount":3},{"hno":22025,"hnm":"강남역우정에쉐르(주상복합)","typeNm":"아파트","callPrice":3146.83,"realPrice":2996.78,"kbPrice":2892.32,"call_KB":108.79,"real_KB":103.61,"callCount":3,"realCount":2},{"hno":22773,"hnm":"역삼SK리더스뷰","typeNm":"오피스텔","callPrice":2795.67,"realPrice":2458.75,"kbPrice":2427.28,"call_KB":115.17,"real_KB":101.29,"callCount":7,"realCount":2},{"hno":108510,"hnm":"강남역이스턴(도시형)","typeNm":"아파트","callPrice":2743.51,"realPrice":2602.14,"kbPrice":2620.92,"call_KB":104.67,"real_KB":99.28,"callCount":7,"realCount":1},{"hno":121224,"hnm":"강남역투웨니퍼스트","typeNm":"오피스텔","callPrice":2662.57,"realPrice":2630.03,"kbPrice":2640.02,"call_KB":100.85,"real_KB":99.62,"callCount":11,"realCount":4},{"hno":3054,"hnm":"역삼한스빌","typeNm":"아파트","callPrice":2592.45,"realPrice":2286.12,"kbPrice":2306.69,"call_KB":112.38,"real_KB":99.1,"callCount":7,"realCount":3},{"hno":12828,"hnm":"우림루미아트(주상복합)","typeNm":"아파트","callPrice":2564.73,"realPrice":null,"kbPrice":2316.66,"call_KB":110.7,"real_KB":null,"callCount":9,"realCount":0},{"hno":3055,"hnm":"한화진넥스빌(주상복합)","typeNm":"아파트","callPrice":2522.58,"realPrice":2332.61,"kbPrice":2463.76,"call_KB":102.38,"real_KB":94.67,"callCount":34,"realCount":2},{"hno":112387,"hnm":"비엘106","typeNm":"오피스텔","callPrice":2457.15,"realPrice":2411.96,"kbPrice":2452.69,"call_KB":100.18,"real_KB":98.33,"callCount":18,"realCount":2},{"hno":13118,"hnm":"대우디오빌플러스(주상복합)","typeNm":"아파트","callPrice":2406.68,"realPrice":null,"kbPrice":2368.37,"call_KB":101.61,"real_KB":null,"callCount":7,"realCount":0},{"hno":13174,"hnm":"진넥스빌2(주상복합)","typeNm":"아파트","callPrice":2267.55,"realPrice":null,"kbPrice":2184.8,"call_KB":103.78,"real_KB":null,"callCount":3,"realCount":0},{"hno":22056,"hnm":"쌍용플래티넘밸류","typeNm":"오피스텔","callPrice":2261.95,"realPrice":2033.63,"kbPrice":1794.28,"call_KB":126.06,"real_KB":113.33,"callCount":5,"realCount":1},{"hno":104714,"hnm":"신논현마에스트로","typeNm":"오피스텔","callPrice":2188.64,"realPrice":null,"kbPrice":2103.38,"call_KB":104.05,"real_KB":null,"callCount":6,"realCount":0},{"hno":25265,"hnm":"역삼디오슈페리움","typeNm":"오피스텔","callPrice":2101.42,"realPrice":null,"kbPrice":1995.05,"call_KB":105.33,"real_KB":null,"callCount":7,"realCount":0},{"hno":105544,"hnm":"강남역센트럴푸르지오시티","typeNm":"오피스텔","callPrice":2084.21,"realPrice":2168.5,"kbPrice":2090.03,"call_KB":99.72,"real_KB":103.75,"callCount":25,"realCount":0},{"hno":107866,"hnm":"역삼푸르지오시티","typeNm":"오피스텔","callPrice":1871.03,"realPrice":1696.97,"kbPrice":1891.11,"call_KB":98.93,"real_KB":89.73,"callCount":28,"realCount":4},{"hno":104445,"hnm":"강남역효성해링턴타워더퍼스트","typeNm":"오피스텔","callPrice":1812.47,"realPrice":1701.41,"kbPrice":1826.99,"call_KB":99.2,"real_KB":93.12,"callCount":14,"realCount":1},{"hno":9461,"hnm":"목화밀라트","typeNm":"오피스텔","callPrice":1807.79,"realPrice":1796.49,"kbPrice":1694.8,"call_KB":106.66,"real_KB":106,"callCount":1,"realCount":1},{"hno":113716,"hnm":"역삼역센트럴푸르지오시티","typeNm":"오피스텔","callPrice":1802.17,"realPrice":1679.78,"kbPrice":1755.19,"call_KB":102.67,"real_KB":95.7,"callCount":22,"realCount":9},{"hno":12503,"hnm":"성우스타우스","typeNm":"오피스텔","callPrice":1625.88,"realPrice":1420.83,"kbPrice":1452.63,"call_KB":111.92,"real_KB":97.81,"callCount":13,"realCount":8},{"hno":21904,"hnm":"대우디오빌플러스","typeNm":"오피스텔","callPrice":1625.71,"realPrice":1648.58,"kbPrice":1610.22,"call_KB":100.96,"real_KB":102.38,"callCount":16,"realCount":4},{"hno":104480,"hnm":"강남역쉐르빌","typeNm":"오피스텔","callPrice":1624.17,"realPrice":1598.6,"kbPrice":1651.79,"call_KB":98.32,"real_KB":96.77,"callCount":12,"realCount":2},{"hno":12505,"hnm":"예성아이라이프","typeNm":"오피스텔","callPrice":1533.59,"realPrice":1549.6,"kbPrice":1522.11,"call_KB":100.75,"real_KB":101.8,"callCount":2,"realCount":2},{"hno":105174,"hnm":"역삼마에스트로","typeNm":"오피스텔","callPrice":1519.93,"realPrice":null,"kbPrice":1546.84,"call_KB":98.26,"real_KB":null,"callCount":6,"realCount":0},{"hno":12501,"hnm":"삼환아르누보","typeNm":"오피스텔","callPrice":1511.99,"realPrice":null,"kbPrice":1511.99,"call_KB":100,"real_KB":null,"callCount":3,"realCount":0},{"hno":9105,"hnm":"능현(선릉대우디오빌3차)","typeNm":"오피스텔","callPrice":1507.94,"realPrice":1574.28,"kbPrice":1449.28,"call_KB":104.04,"real_KB":108.62,"callCount":6,"realCount":1},{"hno":104166,"hnm":"강남역와이즈플레이스","typeNm":"오피스텔","callPrice":1493.97,"realPrice":1444.17,"kbPrice":1576.97,"call_KB":94.73,"real_KB":91.57,"callCount":10,"realCount":2},{"hno":12506,"hnm":"크레신타워2","typeNm":"오피스텔","callPrice":1440.08,"realPrice":1315.53,"kbPrice":1327.97,"call_KB":108.44,"real_KB":99.06,"callCount":10,"realCount":2},{"hno":12502,"hnm":"금천빌딩(선릉이스타빌)","typeNm":"오피스텔","callPrice":1408.71,"realPrice":1441.12,"kbPrice":1397.2,"call_KB":100.82,"real_KB":103.14,"callCount":5,"realCount":1},{"hno":12258,"hnm":"메가시티","typeNm":"오피스텔","callPrice":1406.4,"realPrice":1279.14,"kbPrice":1365.51,"call_KB":102.99,"real_KB":93.67,"callCount":3,"realCount":2},{"hno":17833,"hnm":"네스빌","typeNm":"오피스텔","callPrice":1365.5,"realPrice":1340.9,"kbPrice":1291.69,"call_KB":105.71,"real_KB":103.8,"callCount":1,"realCount":3},{"hno":12498,"hnm":"역삼SK허브블루","typeNm":"오피스텔","callPrice":1361.78,"realPrice":1114.69,"kbPrice":1235.63,"call_KB":110.2,"real_KB":90.21,"callCount":4,"realCount":2},{"hno":12500,"hnm":"강남역두산위브센티움","typeNm":"오피스텔","callPrice":1304.58,"realPrice":1194.92,"kbPrice":1278.49,"call_KB":102.04,"real_KB":93.46,"callCount":12,"realCount":5},{"hno":102529,"hnm":"강남역서희스타힐스","typeNm":"오피스텔","callPrice":1263.46,"realPrice":1152.78,"kbPrice":1241.41,"call_KB":101.77,"real_KB":92.86,"callCount":14,"realCount":1},{"hno":13938,"hnm":"역삼LG에클라트","typeNm":"오피스텔","callPrice":1254.1,"realPrice":1214.55,"kbPrice":1333.15,"call_KB":94.07,"real_KB":91.1,"callCount":7,"realCount":5},{"hno":12504,"hnm":"신일유토빌","typeNm":"오피스텔","callPrice":1222.33,"realPrice":1099.62,"kbPrice":1161.87,"call_KB":105.2,"real_KB":94.64,"callCount":9,"realCount":2},{"hno":12271,"hnm":"역삼현대벤쳐텔","typeNm":"오피스텔","callPrice":1197.68,"realPrice":null,"kbPrice":881.82,"call_KB":135.81,"real_KB":null,"callCount":6,"realCount":0},{"hno":19323,"hnm":"메이플라워멤버스빌","typeNm":"오피스텔","callPrice":1102.37,"realPrice":1115.09,"kbPrice":1154.32,"call_KB":95.49,"real_KB":96.6,"callCount":7,"realCount":3},{"hno":12257,"hnm":"르메이에르타운","typeNm":"오피스텔","callPrice":1013.78,"realPrice":null,"kbPrice":960.42,"call_KB":105.55,"real_KB":null,"callCount":2,"realCount":0},{"hno":12262,"hnm":"SK허브","typeNm":"오피스텔","callPrice":null,"realPrice":1682.66,"kbPrice":1674.69,"call_KB":null,"real_KB":100.47,"callCount":null,"realCount":3},{"hno":821,"hnm":"은하수","typeNm":"재건축","callPrice":null,"realPrice":7557.65,"kbPrice":6849.12,"call_KB":null,"real_KB":110.34,"callCount":null,"realCount":1}]