[{"hno":3751,"hnm":"잠실한솔","typeNm":"아파트","callPrice":4690.35,"realPrice":4388.46,"kbPrice":4437.61,"call_KB":105.69,"real_KB":98.89,"callCount":11,"realCount":3},{"hno":22950,"hnm":"미켈란호수가(주상복합)","typeNm":"아파트","callPrice":4657.84,"realPrice":null,"kbPrice":3777.79,"call_KB":123.29,"real_KB":null,"callCount":5,"realCount":0},{"hno":110709,"hnm":"석촌호수효성해링턴타워(도시형)","typeNm":"아파트","callPrice":3086.86,"realPrice":3003.2,"kbPrice":2930.7,"call_KB":105.32,"real_KB":102.47,"callCount":28,"realCount":3},{"hno":111042,"hnm":"석촌호수나인파크","typeNm":"오피스텔","callPrice":1535.34,"realPrice":1563.81,"kbPrice":1544.98,"call_KB":99.37,"real_KB":101.21,"callCount":36,"realCount":6}]