[{"hno":123319,"hnm":"주안역센트레빌","typeNm":"아파트","callPrice":1629.25,"realPrice":1493.6,"kbPrice":1511.27,"call_KB":107.8,"real_KB":98.83,"callCount":78,"realCount":36},{"hno":126434,"hnm":"주안역신일해피트리","typeNm":"아파트","callPrice":1334.39,"realPrice":null,"kbPrice":1252.97,"call_KB":106.49,"real_KB":null,"callCount":17,"realCount":0},{"hno":22348,"hnm":"주안더월드스테이트","typeNm":"아파트","callPrice":1332.37,"realPrice":1190.17,"kbPrice":1184.07,"call_KB":112.52,"real_KB":100.51,"callCount":126,"realCount":84},{"hno":17560,"hnm":"주안한신휴플러스","typeNm":"아파트","callPrice":1219.13,"realPrice":1050.41,"kbPrice":1108.07,"call_KB":110.02,"real_KB":94.79,"callCount":50,"realCount":3},{"hno":26265,"hnm":"인천관교한신휴플러스","typeNm":"아파트","callPrice":1217.08,"realPrice":1128.05,"kbPrice":1126.11,"call_KB":108.07,"real_KB":100.17,"callCount":74,"realCount":19},{"hno":113320,"hnm":"주안지웰에스테이트(주상복합)","typeNm":"아파트","callPrice":1199.2,"realPrice":1018.48,"kbPrice":1151.43,"call_KB":104.14,"real_KB":88.45,"callCount":30,"realCount":3},{"hno":11522,"hnm":"현대","typeNm":"아파트","callPrice":1187.39,"realPrice":990.25,"kbPrice":1090.75,"call_KB":108.86,"real_KB":90.78,"callCount":9,"realCount":2},{"hno":2444,"hnm":"쌍용주안","typeNm":"아파트","callPrice":1157.17,"realPrice":1027.75,"kbPrice":1070.43,"call_KB":108.1,"real_KB":96.01,"callCount":22,"realCount":5},{"hno":2448,"hnm":"진흥","typeNm":"아파트","callPrice":1104.4,"realPrice":996.53,"kbPrice":1051.03,"call_KB":105.07,"real_KB":94.81,"callCount":45,"realCount":18},{"hno":10690,"hnm":"주안현대홈타운","typeNm":"아파트","callPrice":1094.69,"realPrice":1086.89,"kbPrice":1065.88,"call_KB":102.7,"real_KB":101.97,"callCount":21,"realCount":4},{"hno":14799,"hnm":"남광로얄(1441)","typeNm":"재건축","callPrice":1082.86,"realPrice":845.52,"kbPrice":1053.29,"call_KB":102.8,"real_KB":80.27,"callCount":10,"realCount":-1},{"hno":23072,"hnm":"대산고운누리","typeNm":"아파트","callPrice":1057.43,"realPrice":null,"kbPrice":921.11,"call_KB":114.79,"real_KB":null,"callCount":3,"realCount":0},{"hno":102836,"hnm":"행복마을","typeNm":"아파트","callPrice":1044.34,"realPrice":null,"kbPrice":1055.25,"call_KB":98.96,"real_KB":null,"callCount":3,"realCount":0},{"hno":23616,"hnm":"진도로르빌(주상복합)","typeNm":"아파트","callPrice":1024.18,"realPrice":null,"kbPrice":991.66,"call_KB":103.27,"real_KB":null,"callCount":2,"realCount":0},{"hno":9666,"hnm":"우정(18-141)","typeNm":"아파트","callPrice":1013.26,"realPrice":844.35,"kbPrice":963.28,"call_KB":105.18,"real_KB":87.65,"callCount":9,"realCount":2},{"hno":110316,"hnm":"드림시티(도시형)","typeNm":"아파트","callPrice":1002.23,"realPrice":900.6,"kbPrice":936.67,"call_KB":106.99,"real_KB":96.14,"callCount":3,"realCount":6},{"hno":10475,"hnm":"동인","typeNm":"아파트","callPrice":977.52,"realPrice":801.2,"kbPrice":920.41,"call_KB":106.2,"real_KB":87.04,"callCount":5,"realCount":3},{"hno":2443,"hnm":"남광로얄(1443)","typeNm":"재건축","callPrice":976.35,"realPrice":798.63,"kbPrice":860.98,"call_KB":113.4,"real_KB":92.75,"callCount":37,"realCount":6},{"hno":9667,"hnm":"미도","typeNm":"재건축","callPrice":945.25,"realPrice":662.28,"kbPrice":740.17,"call_KB":127.7,"real_KB":89.47,"callCount":8,"realCount":2},{"hno":12803,"hnm":"아주","typeNm":"아파트","callPrice":900.66,"realPrice":null,"kbPrice":942.88,"call_KB":95.52,"real_KB":null,"callCount":1,"realCount":0},{"hno":9680,"hnm":"선정","typeNm":"아파트","callPrice":900.04,"realPrice":null,"kbPrice":904.34,"call_KB":99.52,"real_KB":null,"callCount":7,"realCount":0},{"hno":10532,"hnm":"연흥(1491-3)","typeNm":"아파트","callPrice":891.8,"realPrice":889.72,"kbPrice":808.47,"call_KB":110.3,"real_KB":110.04,"callCount":6,"realCount":2},{"hno":14798,"hnm":"두산(주상복합)","typeNm":"아파트","callPrice":890.81,"realPrice":805.53,"kbPrice":730.72,"call_KB":121.9,"real_KB":110.23,"callCount":5,"realCount":1},{"hno":25095,"hnm":"주안휴먼빌","typeNm":"아파트","callPrice":878.59,"realPrice":856.67,"kbPrice":813.08,"call_KB":108.05,"real_KB":105.36,"callCount":4,"realCount":4},{"hno":13770,"hnm":"광해리드빌(102동,주상복합)","typeNm":"아파트","callPrice":873.64,"realPrice":860.64,"kbPrice":766.76,"call_KB":113.93,"real_KB":112.24,"callCount":4,"realCount":1},{"hno":2442,"hnm":"광명8차","typeNm":"아파트","callPrice":872.79,"realPrice":723.54,"kbPrice":808.62,"call_KB":107.93,"real_KB":89.47,"callCount":7,"realCount":2},{"hno":10620,"hnm":"영동","typeNm":"아파트","callPrice":853.23,"realPrice":664.13,"kbPrice":651.07,"call_KB":131.04,"real_KB":102,"callCount":3,"realCount":3},{"hno":14801,"hnm":"신비마을","typeNm":"아파트","callPrice":845.3,"realPrice":745.71,"kbPrice":792.25,"call_KB":106.69,"real_KB":94.12,"callCount":62,"realCount":3},{"hno":10561,"hnm":"광성(1466-3)","typeNm":"아파트","callPrice":842.99,"realPrice":839.51,"kbPrice":622.44,"call_KB":135.43,"real_KB":134.87,"callCount":7,"realCount":1},{"hno":14793,"hnm":"광명6차","typeNm":"아파트","callPrice":842.63,"realPrice":701.89,"kbPrice":809.25,"call_KB":104.12,"real_KB":86.73,"callCount":5,"realCount":3},{"hno":14071,"hnm":"경민","typeNm":"아파트","callPrice":842.43,"realPrice":749.65,"kbPrice":616.38,"call_KB":136.67,"real_KB":121.62,"callCount":1,"realCount":1},{"hno":12114,"hnm":"석락","typeNm":"아파트","callPrice":836.63,"realPrice":732.85,"kbPrice":910.08,"call_KB":91.92,"real_KB":80.52,"callCount":3,"realCount":1},{"hno":10487,"hnm":"광해리드빌(101동,주상복합)","typeNm":"아파트","callPrice":791.05,"realPrice":758.84,"kbPrice":758.71,"call_KB":104.26,"real_KB":100.01,"callCount":2,"realCount":0},{"hno":16577,"hnm":"현광저층","typeNm":"아파트","callPrice":789.75,"realPrice":null,"kbPrice":627.46,"call_KB":125.86,"real_KB":null,"callCount":6,"realCount":0},{"hno":10471,"hnm":"주안태화2차","typeNm":"아파트","callPrice":786.66,"realPrice":740.53,"kbPrice":712.81,"call_KB":110.36,"real_KB":103.88,"callCount":4,"realCount":2},{"hno":24124,"hnm":"연흥(9-3)","typeNm":"아파트","callPrice":784.2,"realPrice":681.96,"kbPrice":594.04,"call_KB":132.01,"real_KB":114.8,"callCount":4,"realCount":2},{"hno":106254,"hnm":"보미리즌빌(주상복합)","typeNm":"아파트","callPrice":777.96,"realPrice":775.4,"kbPrice":780.51,"call_KB":99.67,"real_KB":99.34,"callCount":6,"realCount":3},{"hno":10476,"hnm":"삼덕진주(6,7,9동)","typeNm":"재건축","callPrice":775.2,"realPrice":null,"kbPrice":752.4,"call_KB":103.03,"real_KB":null,"callCount":1,"realCount":0},{"hno":113321,"hnm":"주안지웰에스테이트","typeNm":"오피스텔","callPrice":774.39,"realPrice":755.03,"kbPrice":774.39,"call_KB":100,"real_KB":97.5,"callCount":11,"realCount":7},{"hno":10411,"hnm":"현광고층","typeNm":"아파트","callPrice":763.74,"realPrice":710.76,"kbPrice":762.16,"call_KB":100.2,"real_KB":93.25,"callCount":6,"realCount":7},{"hno":14802,"hnm":"삼영(1574-2)","typeNm":"재건축","callPrice":758.9,"realPrice":null,"kbPrice":801.06,"call_KB":94.73,"real_KB":null,"callCount":1,"realCount":0},{"hno":14800,"hnm":"시영(주안)","typeNm":"아파트","callPrice":755.04,"realPrice":812.95,"kbPrice":759.58,"call_KB":99.4,"real_KB":107.02,"callCount":8,"realCount":1},{"hno":10410,"hnm":"가람","typeNm":"아파트","callPrice":754.58,"realPrice":639.98,"kbPrice":687.71,"call_KB":109.72,"real_KB":93.05,"callCount":5,"realCount":2},{"hno":10474,"hnm":"광명4차","typeNm":"아파트","callPrice":731.61,"realPrice":744.91,"kbPrice":654.01,"call_KB":111.86,"real_KB":113.89,"callCount":2,"realCount":1},{"hno":9724,"hnm":"삼영(20-21)","typeNm":"아파트","callPrice":727.95,"realPrice":null,"kbPrice":707.25,"call_KB":102.92,"real_KB":null,"callCount":5,"realCount":0},{"hno":14090,"hnm":"남부아주","typeNm":"아파트","callPrice":726.73,"realPrice":682.69,"kbPrice":671.68,"call_KB":108.19,"real_KB":101.63,"callCount":2,"realCount":1},{"hno":104483,"hnm":"삼영(20-14)","typeNm":"아파트","callPrice":695.72,"realPrice":null,"kbPrice":636.76,"call_KB":109.25,"real_KB":null,"callCount":2,"realCount":0},{"hno":9671,"hnm":"삼미","typeNm":"아파트","callPrice":663.05,"realPrice":null,"kbPrice":586.49,"call_KB":113.05,"real_KB":null,"callCount":5,"realCount":0},{"hno":16575,"hnm":"윤성","typeNm":"아파트","callPrice":660.33,"realPrice":706.86,"kbPrice":564.62,"call_KB":116.95,"real_KB":125.19,"callCount":8,"realCount":1},{"hno":8418,"hnm":"한덕(금양)","typeNm":"아파트","callPrice":657.63,"realPrice":638.14,"kbPrice":636.21,"call_KB":103.36,"real_KB":100.3,"callCount":9,"realCount":2},{"hno":101106,"hnm":"신라(757-1)","typeNm":"아파트","callPrice":625.45,"realPrice":516,"kbPrice":580.78,"call_KB":107.69,"real_KB":88.84,"callCount":1,"realCount":1},{"hno":8417,"hnm":"태평","typeNm":"아파트","callPrice":614.74,"realPrice":520.85,"kbPrice":611.46,"call_KB":100.53,"real_KB":85.18,"callCount":11,"realCount":4},{"hno":13236,"hnm":"롯데하이텔(주상복합)","typeNm":"아파트","callPrice":594.28,"realPrice":571.87,"kbPrice":584.08,"call_KB":101.74,"real_KB":97.9,"callCount":1,"realCount":0},{"hno":110317,"hnm":"드림시티","typeNm":"오피스텔","callPrice":566.09,"realPrice":null,"kbPrice":513.26,"call_KB":110.29,"real_KB":null,"callCount":1,"realCount":0},{"hno":14803,"hnm":"욱일","typeNm":"아파트","callPrice":545.44,"realPrice":null,"kbPrice":531.09,"call_KB":102.7,"real_KB":null,"callCount":1,"realCount":0},{"hno":17289,"hnm":"디에이리베로","typeNm":"오피스텔","callPrice":515.46,"realPrice":471.88,"kbPrice":496.71,"call_KB":103.77,"real_KB":95,"callCount":7,"realCount":5},{"hno":13815,"hnm":"경일","typeNm":"아파트","callPrice":505.81,"realPrice":608.66,"kbPrice":573.25,"call_KB":88.23,"real_KB":106.17,"callCount":1,"realCount":4},{"hno":11593,"hnm":"경신","typeNm":"아파트","callPrice":452.46,"realPrice":472.34,"kbPrice":546.43,"call_KB":82.8,"real_KB":86.44,"callCount":1,"realCount":1},{"hno":12452,"hnm":"스페이스이모션","typeNm":"오피스텔","callPrice":442.98,"realPrice":424.92,"kbPrice":442.98,"call_KB":100,"real_KB":95.92,"callCount":2,"realCount":4},{"hno":18820,"hnm":"광해리드빌(102동)","typeNm":"오피스텔","callPrice":440.69,"realPrice":345.75,"kbPrice":389.72,"call_KB":113.07,"real_KB":88.71,"callCount":3,"realCount":1},{"hno":11478,"hnm":"신라(1528-4)","typeNm":"아파트","callPrice":null,"realPrice":773.34,"kbPrice":791.72,"call_KB":null,"real_KB":97.67,"callCount":null,"realCount":2}]