[{"hno":117357,"hnm":"농성SK뷰센트럴","typeNm":"아파트","callPrice":1851.79,"realPrice":1578.42,"kbPrice":1613.32,"call_KB":114.78,"real_KB":97.83,"callCount":121,"realCount":36},{"hno":5520,"hnm":"삼익","typeNm":"아파트","callPrice":994.12,"realPrice":862.79,"kbPrice":807.2,"call_KB":123.15,"real_KB":106.88,"callCount":12,"realCount":6},{"hno":5522,"hnm":"중흥파크","typeNm":"아파트","callPrice":672.54,"realPrice":606.91,"kbPrice":542.89,"call_KB":123.88,"real_KB":111.79,"callCount":2,"realCount":4},{"hno":106339,"hnm":"농성유탑유블레스","typeNm":"아파트","callPrice":607.46,"realPrice":597.15,"kbPrice":632.67,"call_KB":96.01,"real_KB":94.38,"callCount":12,"realCount":8},{"hno":16657,"hnm":"세종","typeNm":"아파트","callPrice":586.89,"realPrice":571.65,"kbPrice":411.59,"call_KB":142.59,"real_KB":138.88,"callCount":3,"realCount":1},{"hno":116944,"hnm":"골든힐스타워","typeNm":"오피스텔","callPrice":470.87,"realPrice":426.65,"kbPrice":459.29,"call_KB":102.52,"real_KB":92.89,"callCount":3,"realCount":3},{"hno":5521,"hnm":"제일파크","typeNm":"아파트","callPrice":null,"realPrice":526.77,"kbPrice":503.53,"call_KB":null,"real_KB":104.61,"callCount":null,"realCount":2}]