[{"hno":111455,"hnm":"도룡KCC웰츠타워","typeNm":"오피스텔","callPrice":"957.48","realPrice":"없음","kbPrice":970.97,"call_KB":"98.61","real_KB":"없음","callCount":13,"realCount":0,"naver_link":"https://new.land.naver.com/complexes/111455"},{"hno":119934,"hnm":"도룡코아루스마트리치","typeNm":"오피스텔","callPrice":"934.51","realPrice":"798.83","kbPrice":868.88,"call_KB":"107.55","real_KB":"91.93","callCount":25,"realCount":2,"naver_link":"https://new.land.naver.com/complexes/119934"},{"hno":118931,"hnm":"도룡하우스디어반","typeNm":"오피스텔","callPrice":"810.15","realPrice":"745.26","kbPrice":802.31,"call_KB":"100.97","real_KB":"92.88","callCount":58,"realCount":1,"naver_link":"https://new.land.naver.com/complexes/118931"},{"hno":26339,"hnm":"도룡로덴하우스","typeNm":"아파트","callPrice":"3539.08","realPrice":"없음","kbPrice":2292.92,"call_KB":"154.34","real_KB":"없음","callCount":2,"realCount":0,"naver_link":"https://new.land.naver.com/complexes/26339"},{"hno":114293,"hnm":"도룡SK뷰","typeNm":"아파트","callPrice":"3535.37","realPrice":"2978.70","kbPrice":2780.81,"call_KB":"127.13","real_KB":"107.11","callCount":33,"realCount":9,"naver_link":"https://new.land.naver.com/complexes/114293"},{"hno":23993,"hnm":"스마트시티5단지(주상복합)","typeNm":"아파트","callPrice":"2596.88","realPrice":"3391.30","kbPrice":2934.55,"call_KB":"88.49","real_KB":"115.56","callCount":20,"realCount":7,"naver_link":"https://new.land.naver.com/complexes/23993"},{"hno":10948,"hnm":"우성","typeNm":"아파트","callPrice":"2488.92","realPrice":"없음","kbPrice":1848.91,"call_KB":"134.61","real_KB":"없음","callCount":3,"realCount":0,"naver_link":"https://new.land.naver.com/complexes/10948"},{"hno":9343,"hnm":"연구원현대","typeNm":"아파트","callPrice":"2472.97","realPrice":"없음","kbPrice":1905.41,"call_KB":"129.78","real_KB":"없음","callCount":10,"realCount":0,"naver_link":"https://new.land.naver.com/complexes/9343"},{"hno":101298,"hnm":"스마트시티2단지(주상복합)","typeNm":"아파트","callPrice":"2407.03","realPrice":"3396.95","kbPrice":2814.95,"call_KB":"85.50","real_KB":"120.67","callCount":12,"realCount":9,"naver_link":"https://new.land.naver.com/complexes/101298"},{"hno":107927,"hnm":"스마트시티리버뷰","typeNm":"오피스텔","callPrice":"1272.44","realPrice":"1162.70","kbPrice":1072.46,"call_KB":"118.64","real_KB":"108.41","callCount":30,"realCount":3,"naver_link":"https://new.land.naver.com/complexes/107927"},{"hno":128217,"hnm":"스타빌플러스(도시형)","typeNm":"아파트","callPrice":"1203.89","realPrice":"없음","kbPrice":1233.69,"call_KB":"97.58","real_KB":"없음","callCount":12,"realCount":0,"naver_link":"https://new.land.naver.com/complexes/128217"}]