[{"hno":6143,"hnm":"한마을","typeNm":"아파트","callPrice":936.33,"realPrice":868.97,"kbPrice":880.43,"call_KB":106.34,"real_KB":98.69,"callCount":36,"realCount":29},{"hno":25256,"hnm":"송강그린","typeNm":"아파트","callPrice":811.99,"realPrice":736.89,"kbPrice":780.92,"call_KB":103.97,"real_KB":94.36,"callCount":61,"realCount":61},{"hno":6144,"hnm":"청솔(한양)","typeNm":"아파트","callPrice":733.63,"realPrice":676.43,"kbPrice":707.98,"call_KB":103.62,"real_KB":95.54,"callCount":27,"realCount":13},{"hno":24761,"hnm":"한솔","typeNm":"아파트","callPrice":702.66,"realPrice":632.37,"kbPrice":663.42,"call_KB":105.91,"real_KB":95.31,"callCount":41,"realCount":28},{"hno":6142,"hnm":"청솔(뉴서울,신호,태영)","typeNm":"아파트","callPrice":701.22,"realPrice":623.73,"kbPrice":672.74,"call_KB":104.23,"real_KB":92.71,"callCount":14,"realCount":44},{"hno":6140,"hnm":"송강마을2단지","typeNm":"아파트","callPrice":606.71,"realPrice":575.79,"kbPrice":580.04,"call_KB":104.59,"real_KB":99.26,"callCount":30,"realCount":30}]