[{"hno":105653,"hnm":"가재12단지중흥S-클래스센텀파크2차","typeNm":"아파트","callPrice":"1952.72","realPrice":"1528.66","kbPrice":1810.7,"call_KB":"107.84","real_KB":"84.42","callCount":69,"realCount":18,"naver_link":"https://new.land.naver.com/complexes/105653"},{"hno":104541,"hnm":"가재마을7단지중흥S-클래스센텀파크1차","typeNm":"아파트","callPrice":"1936.65","realPrice":"1716.69","kbPrice":1798.59,"call_KB":"107.67","real_KB":"95.44","callCount":33,"realCount":13,"naver_link":"https://new.land.naver.com/complexes/104541"},{"hno":104343,"hnm":"가재9단지세종한신휴플러스리버파크","typeNm":"아파트","callPrice":"1907.74","realPrice":"1698.58","kbPrice":1744.12,"call_KB":"109.38","real_KB":"97.38","callCount":56,"realCount":11,"naver_link":"https://new.land.naver.com/complexes/104343"},{"hno":105549,"hnm":"가재10단지제일풍경채에듀파크","typeNm":"아파트","callPrice":"1848.81","realPrice":"1845.39","kbPrice":1669.51,"call_KB":"110.73","real_KB":"110.53","callCount":28,"realCount":4,"naver_link":"https://new.land.naver.com/complexes/105549"},{"hno":105551,"hnm":"가재3단지중흥S-클래스에듀타운","typeNm":"아파트","callPrice":"1813.02","realPrice":"1483.17","kbPrice":1577.17,"call_KB":"114.95","real_KB":"94.04","callCount":29,"realCount":6,"naver_link":"https://new.land.naver.com/complexes/105551"},{"hno":104423,"hnm":"가재마을5단지세종엠코타운","typeNm":"아파트","callPrice":"1770.36","realPrice":"1653.81","kbPrice":1678.29,"call_KB":"105.48","real_KB":"98.54","callCount":104,"realCount":37,"naver_link":"https://new.land.naver.com/complexes/104423"},{"hno":104261,"hnm":"가재11단지한신휴플러스","typeNm":"아파트","callPrice":"1721.28","realPrice":"1618.11","kbPrice":1628.33,"call_KB":"105.70","real_KB":"99.37","callCount":38,"realCount":11,"naver_link":"https://new.land.naver.com/complexes/104261"},{"hno":106116,"hnm":"가재2단지베르디움","typeNm":"아파트","callPrice":"1699.37","realPrice":"1589.13","kbPrice":1555.69,"call_KB":"109.23","real_KB":"102.14","callCount":25,"realCount":7,"naver_link":"https://new.land.naver.com/complexes/106116"},{"hno":137451,"hnm":"가재8단지세경","typeNm":"아파트","callPrice":"1522.96","realPrice":"없음","kbPrice":1398.24,"call_KB":"108.91","real_KB":"없음","callCount":26,"realCount":0,"naver_link":"https://new.land.naver.com/complexes/137451"},{"hno":107083,"hnm":"가재4단지세종센트레빌","typeNm":"아파트","callPrice":"1517.46","realPrice":"1411.84","kbPrice":1410.86,"call_KB":"107.55","real_KB":"100.06","callCount":69,"realCount":28,"naver_link":"https://new.land.naver.com/complexes/107083"},{"hno":137104,"hnm":"가재6단지세경","typeNm":"아파트","callPrice":"1334.43","realPrice":"1218.65","kbPrice":1236.58,"call_KB":"107.91","real_KB":"98.54","callCount":12,"realCount":12,"naver_link":"https://new.land.naver.com/complexes/137104"}]