[{"hno":4751,"hnm":"풍덕주공","typeNm":"아파트","callPrice":"607.72","realPrice":"554.87","kbPrice":607.72,"call_KB":"100.00","real_KB":"91.30","callCount":2,"realCount":1,"naver_link":"https://new.land.naver.com/complexes/4751"},{"hno":4752,"hnm":"한신","typeNm":"아파트","callPrice":"176.18","realPrice":"529.58","kbPrice":491.65,"call_KB":"35.83","real_KB":"107.71","callCount":2,"realCount":7,"naver_link":"https://new.land.naver.com/complexes/4752"},{"hno":4747,"hnm":"금호","typeNm":"아파트","callPrice":"0.00","realPrice":"474.68","kbPrice":460.66,"call_KB":"0.00","real_KB":"103.04","callCount":0,"realCount":6,"naver_link":"https://new.land.naver.com/complexes/4747"}]