[{"hno":109914,"hnm":"문성파크자이","typeNm":"아파트","callPrice":"953.87","realPrice":"961.10","kbPrice":975.65,"call_KB":"97.76","real_KB":"98.50","callCount":53,"realCount":32,"naver_link":"https://new.land.naver.com/complexes/109914"},{"hno":106945,"hnm":"구미고아세영리첼레이크뷰","typeNm":"아파트","callPrice":"887.01","realPrice":"819.88","kbPrice":850.6,"call_KB":"104.27","real_KB":"96.38","callCount":45,"realCount":14,"naver_link":"https://new.land.naver.com/complexes/106945"},{"hno":110111,"hnm":"문성서희스타힐스","typeNm":"아파트","callPrice":"841.43","realPrice":"768.07","kbPrice":808.42,"call_KB":"104.08","real_KB":"95.00","callCount":57,"realCount":30,"naver_link":"https://new.land.naver.com/complexes/110111"},{"hno":27061,"hnm":"구미문성경남아너스빌","typeNm":"아파트","callPrice":"802.72","realPrice":"724.73","kbPrice":730.8,"call_KB":"109.84","real_KB":"99.17","callCount":31,"realCount":12,"naver_link":"https://new.land.naver.com/complexes/27061"},{"hno":107851,"hnm":"문성지구태왕아너스","typeNm":"아파트","callPrice":"704.73","realPrice":"663.76","kbPrice":651.73,"call_KB":"108.13","real_KB":"101.84","callCount":7,"realCount":1,"naver_link":"https://new.land.naver.com/complexes/107851"},{"hno":27062,"hnm":"구미원호푸르지오","typeNm":"아파트","callPrice":"680.35","realPrice":"731.34","kbPrice":776.31,"call_KB":"87.63","real_KB":"94.20","callCount":41,"realCount":15,"naver_link":"https://new.land.naver.com/complexes/27062"},{"hno":4180,"hnm":"구미원호대우","typeNm":"아파트","callPrice":"609.82","realPrice":"574.27","kbPrice":570.22,"call_KB":"106.94","real_KB":"100.70","callCount":3,"realCount":8,"naver_link":"https://new.land.naver.com/complexes/4180"},{"hno":4181,"hnm":"원호점보타운","typeNm":"아파트","callPrice":"363.43","realPrice":"345.42","kbPrice":379.5,"call_KB":"95.76","real_KB":"91.01","callCount":33,"realCount":19,"naver_link":"https://new.land.naver.com/complexes/4181"},{"hno":4182,"hnm":"원호한누리타운2단지","typeNm":"아파트","callPrice":"356.15","realPrice":"354.36","kbPrice":381.69,"call_KB":"93.30","real_KB":"92.84","callCount":27,"realCount":18,"naver_link":"https://new.land.naver.com/complexes/4182"},{"hno":4185,"hnm":"청솔타운","typeNm":"아파트","callPrice":"269.30","realPrice":"269.36","kbPrice":241.46,"call_KB":"111.53","real_KB":"111.55","callCount":9,"realCount":3,"naver_link":"https://new.land.naver.com/complexes/4185"},{"hno":4184,"hnm":"원호한누리타운3단지","typeNm":"아파트","callPrice":"234.57","realPrice":"453.70","kbPrice":486.17,"call_KB":"48.24","real_KB":"93.32","callCount":27,"realCount":14,"naver_link":"https://new.land.naver.com/complexes/4184"},{"hno":15540,"hnm":"삼우힐타운","typeNm":"아파트","callPrice":"222.43","realPrice":"209.57","kbPrice":205.11,"call_KB":"108.44","real_KB":"102.17","callCount":13,"realCount":2,"naver_link":"https://new.land.naver.com/complexes/15540"},{"hno":101971,"hnm":"고아에덴타운","typeNm":"아파트","callPrice":"219.51","realPrice":"215.72","kbPrice":208.9,"call_KB":"105.07","real_KB":"103.26","callCount":8,"realCount":15,"naver_link":"https://new.land.naver.com/complexes/101971"},{"hno":122878,"hnm":"문성레이크자이","typeNm":"아파트","callPrice":"1372.14","realPrice":"1258.67","kbPrice":1225.35,"call_KB":"111.97","real_KB":"102.71","callCount":42,"realCount":23,"naver_link":"https://new.land.naver.com/complexes/122878"},{"hno":104497,"hnm":"괴평무지개","typeNm":"아파트","callPrice":"130.02","realPrice":"259.62","kbPrice":206.37,"call_KB":"63.00","real_KB":"125.80","callCount":2,"realCount":2,"naver_link":"https://new.land.naver.com/complexes/104497"},{"hno":15539,"hnm":"럭키","typeNm":"아파트","callPrice":"0.00","realPrice":"125.22","kbPrice":139.28,"call_KB":"0.00","real_KB":"89.90","callCount":0,"realCount":3,"naver_link":"https://new.land.naver.com/complexes/15539"}]