[{"sno":4812710600,"snm":"합성동","callPrice":1231.33,"realPrice":997.65,"kbPrice":951.66,"call_KB":129.38,"real_KB":104.83,"callCount":59,"realCount":31},{"sno":4812710400,"snm":"석전동","callPrice":1089.01,"realPrice":1018.5,"kbPrice":948.83,"call_KB":114.77,"real_KB":107.34,"callCount":90,"realCount":47},{"sno":4812710500,"snm":"양덕동","callPrice":998.63,"realPrice":944.41,"kbPrice":867.54,"call_KB":115.11,"real_KB":108.86,"callCount":467,"realCount":225},{"sno":4812710100,"snm":"구암동","callPrice":669.25,"realPrice":648.03,"kbPrice":656.77,"call_KB":101.89,"real_KB":98.66,"callCount":36,"realCount":33},{"sno":4812710800,"snm":"회원동","callPrice":623.87,"realPrice":607.89,"kbPrice":581.13,"call_KB":107.35,"real_KB":104.6,"callCount":24,"realCount":19},{"sno":4812725000,"snm":"내서읍","callPrice":589.81,"realPrice":553.14,"kbPrice":541.53,"call_KB":108.91,"real_KB":102.14,"callCount":286,"realCount":264},{"sno":4812710300,"snm":"봉암동","callPrice":449.43,"realPrice":438.55,"kbPrice":428.4,"call_KB":104.91,"real_KB":102.36,"callCount":15,"realCount":7}]