[{"hno":120065,"hnm":"진주혁신도시중흥S-클래스더퍼스트","typeNm":"아파트","callPrice":"2011.12","realPrice":"1896.75","kbPrice":1916.66,"call_KB":"104.92","real_KB":"98.96","callCount":47,"realCount":19,"naver_link":"https://new.land.naver.com/complexes/120065"},{"hno":115359,"hnm":"진주혁신도시대방노블랜드더캐슬","typeNm":"아파트","callPrice":"1886.68","realPrice":"1774.17","kbPrice":1761.13,"call_KB":"107.12","real_KB":"100.74","callCount":50,"realCount":30,"naver_link":"https://new.land.naver.com/complexes/115359"},{"hno":117640,"hnm":"진주혁신도시중흥S-클래스센트럴시티2단지(주상복합)","typeNm":"아파트","callPrice":"1725.97","realPrice":"1578.80","kbPrice":1584.62,"call_KB":"108.92","real_KB":"99.63","callCount":44,"realCount":23,"naver_link":"https://new.land.naver.com/complexes/117640"},{"hno":117642,"hnm":"진주혁신도시중흥S-클래스센트럴시티4단지(주상복합)","typeNm":"아파트","callPrice":"1679.61","realPrice":"1467.88","kbPrice":1549.82,"call_KB":"108.37","real_KB":"94.71","callCount":49,"realCount":15,"naver_link":"https://new.land.naver.com/complexes/117642"},{"hno":117641,"hnm":"진주혁신도시중흥S-클래스센트럴시티3단지(주상복합)","typeNm":"아파트","callPrice":"1674.88","realPrice":"1497.74","kbPrice":1542.7,"call_KB":"108.56","real_KB":"97.08","callCount":31,"realCount":17,"naver_link":"https://new.land.naver.com/complexes/117641"},{"hno":115519,"hnm":"진주혁신도시중흥S-클래스더프라임","typeNm":"아파트","callPrice":"1668.58","realPrice":"1508.09","kbPrice":1579.56,"call_KB":"105.63","real_KB":"95.47","callCount":51,"realCount":40,"naver_link":"https://new.land.naver.com/complexes/115519"},{"hno":112817,"hnm":"라온프라이빗","typeNm":"아파트","callPrice":"1543.23","realPrice":"1428.15","kbPrice":1357.11,"call_KB":"113.71","real_KB":"105.23","callCount":24,"realCount":11,"naver_link":"https://new.land.naver.com/complexes/112817"},{"hno":107027,"hnm":"한림풀에버","typeNm":"아파트","callPrice":"1315.89","realPrice":"1199.90","kbPrice":1195.9,"call_KB":"110.03","real_KB":"100.33","callCount":47,"realCount":31,"naver_link":"https://new.land.naver.com/complexes/107027"},{"hno":115522,"hnm":"휴앤인엘리시움(주상복합)","typeNm":"아파트","callPrice":"1300.50","realPrice":"1072.59","kbPrice":1124.46,"call_KB":"115.65","real_KB":"95.38","callCount":7,"realCount":3,"naver_link":"https://new.land.naver.com/complexes/115522"},{"hno":110637,"hnm":"혁신도시LH9단지","typeNm":"아파트","callPrice":"1288.07","realPrice":"1223.74","kbPrice":1243.15,"call_KB":"103.61","real_KB":"98.43","callCount":34,"realCount":39,"naver_link":"https://new.land.naver.com/complexes/110637"},{"hno":107705,"hnm":"혁신도시LH8단지","typeNm":"아파트","callPrice":"1209.74","realPrice":"1170.43","kbPrice":1148.31,"call_KB":"105.34","real_KB":"101.92","callCount":67,"realCount":37,"naver_link":"https://new.land.naver.com/complexes/107705"},{"hno":107003,"hnm":"진주혁신코오롱하늘채","typeNm":"아파트","callPrice":"1208.00","realPrice":"1122.68","kbPrice":1140.28,"call_KB":"105.93","real_KB":"98.45","callCount":61,"realCount":36,"naver_link":"https://new.land.naver.com/complexes/107003"},{"hno":137446,"hnm":"혁신도시LH5단지","typeNm":"아파트","callPrice":"1174.85","realPrice":"없음","kbPrice":1107.85,"call_KB":"106.04","real_KB":"없음","callCount":19,"realCount":0,"naver_link":"https://new.land.naver.com/complexes/137446"},{"hno":107002,"hnm":"진주혁신도시센텀리버파크","typeNm":"아파트","callPrice":"1040.59","realPrice":"1105.96","kbPrice":1138.59,"call_KB":"91.39","real_KB":"97.13","callCount":31,"realCount":15,"naver_link":"https://new.land.naver.com/complexes/107002"}]