[{"hno":127572,"hnm":"e편한세상거제유로아일랜드","typeNm":"아파트","callPrice":1244.87,"realPrice":null,"kbPrice":1154.6,"call_KB":107.81,"real_KB":null,"callCount":37,"realCount":0},{"hno":15276,"hnm":"고현주공","typeNm":"아파트","callPrice":984.27,"realPrice":843.14,"kbPrice":941.13,"call_KB":104.58,"real_KB":89.58,"callCount":9,"realCount":5},{"hno":19330,"hnm":"거제롯데인벤스가","typeNm":"아파트","callPrice":895.85,"realPrice":null,"kbPrice":885.02,"call_KB":101.22,"real_KB":null,"callCount":11,"realCount":0},{"hno":111724,"hnm":"스타힐스센트럴","typeNm":"아파트","callPrice":743.23,"realPrice":690.16,"kbPrice":697.22,"call_KB":106.6,"real_KB":98.98,"callCount":24,"realCount":10},{"hno":5924,"hnm":"화인아트","typeNm":"아파트","callPrice":729.64,"realPrice":null,"kbPrice":812.5,"call_KB":89.8,"real_KB":null,"callCount":15,"realCount":0},{"hno":110073,"hnm":"e편한세상고현","typeNm":"아파트","callPrice":713.74,"realPrice":665.52,"kbPrice":708.31,"call_KB":100.76,"real_KB":93.95,"callCount":12,"realCount":9},{"hno":101055,"hnm":"거제양정대동피렌체","typeNm":"아파트","callPrice":547.75,"realPrice":567.07,"kbPrice":600.63,"call_KB":91.19,"real_KB":94.41,"callCount":12,"realCount":5},{"hno":102452,"hnm":"고려3차(1050)","typeNm":"아파트","callPrice":542.18,"realPrice":null,"kbPrice":523.87,"call_KB":103.49,"real_KB":null,"callCount":6,"realCount":0},{"hno":5884,"hnm":"고려5차","typeNm":"아파트","callPrice":531.74,"realPrice":513.42,"kbPrice":555.5,"call_KB":95.72,"real_KB":92.42,"callCount":9,"realCount":3},{"hno":16477,"hnm":"고려6차","typeNm":"아파트","callPrice":522.7,"realPrice":514.69,"kbPrice":549.7,"call_KB":95.08,"real_KB":93.63,"callCount":13,"realCount":2},{"hno":15290,"hnm":"삼성하이츠","typeNm":"아파트","callPrice":508.4,"realPrice":null,"kbPrice":530.25,"call_KB":95.87,"real_KB":null,"callCount":9,"realCount":0},{"hno":5875,"hnm":"고려4차","typeNm":"아파트","callPrice":505.6,"realPrice":516.55,"kbPrice":555.2,"call_KB":91.06,"real_KB":93.03,"callCount":14,"realCount":4},{"hno":101679,"hnm":"화인","typeNm":"아파트","callPrice":502.23,"realPrice":470.61,"kbPrice":482.82,"call_KB":104.01,"real_KB":97.47,"callCount":3,"realCount":1},{"hno":103989,"hnm":"주영에이스빌","typeNm":"아파트","callPrice":495.83,"realPrice":null,"kbPrice":518.68,"call_KB":95.59,"real_KB":null,"callCount":3,"realCount":0},{"hno":100959,"hnm":"일성수월아리채","typeNm":"아파트","callPrice":495.75,"realPrice":475.03,"kbPrice":562.34,"call_KB":88.15,"real_KB":84.47,"callCount":2,"realCount":2},{"hno":5908,"hnm":"덕산베스트타운","typeNm":"아파트","callPrice":495.37,"realPrice":498.67,"kbPrice":512.62,"call_KB":96.63,"real_KB":97.27,"callCount":57,"realCount":29},{"hno":15292,"hnm":"신우성","typeNm":"아파트","callPrice":483.71,"realPrice":null,"kbPrice":514.01,"call_KB":94.1,"real_KB":null,"callCount":5,"realCount":0},{"hno":5848,"hnm":"고려2차","typeNm":"아파트","callPrice":476.5,"realPrice":null,"kbPrice":528.24,"call_KB":90.2,"real_KB":null,"callCount":6,"realCount":0},{"hno":5843,"hnm":"고려1차","typeNm":"아파트","callPrice":468.5,"realPrice":436.56,"kbPrice":492.18,"call_KB":95.18,"real_KB":88.69,"callCount":4,"realCount":1},{"hno":101959,"hnm":"신원파크뷰","typeNm":"아파트","callPrice":458.99,"realPrice":null,"kbPrice":520.19,"call_KB":88.23,"real_KB":null,"callCount":1,"realCount":0},{"hno":101000,"hnm":"거제덕산베스트타운2차","typeNm":"아파트","callPrice":450.02,"realPrice":443.5,"kbPrice":474.27,"call_KB":94.88,"real_KB":93.51,"callCount":34,"realCount":24},{"hno":15284,"hnm":"동헌","typeNm":"아파트","callPrice":429.19,"realPrice":416.25,"kbPrice":476.98,"call_KB":89.98,"real_KB":87.26,"callCount":4,"realCount":2},{"hno":101677,"hnm":"덕진휴먼빌","typeNm":"아파트","callPrice":380.17,"realPrice":406.05,"kbPrice":381.87,"call_KB":99.55,"real_KB":106.33,"callCount":3,"realCount":2},{"hno":111951,"hnm":"골든아틀란티스","typeNm":"오피스텔","callPrice":377.28,"realPrice":357.7,"kbPrice":462.95,"call_KB":81.49,"real_KB":77.26,"callCount":1,"realCount":3},{"hno":15275,"hnm":"고려3차(963-12)","typeNm":"아파트","callPrice":null,"realPrice":343.76,"kbPrice":466.53,"call_KB":null,"real_KB":73.68,"callCount":null,"realCount":1},{"hno":15286,"hnm":"고현삼도","typeNm":"아파트","callPrice":null,"realPrice":355.93,"kbPrice":377.64,"call_KB":null,"real_KB":94.25,"callCount":null,"realCount":2},{"hno":110461,"hnm":"한미비치빌","typeNm":"아파트","callPrice":null,"realPrice":460.07,"kbPrice":492.72,"call_KB":null,"real_KB":93.37,"callCount":null,"realCount":1},{"hno":104705,"hnm":"나인스카이시티","typeNm":"오피스텔","callPrice":null,"realPrice":198.61,"kbPrice":352.26,"call_KB":null,"real_KB":56.38,"callCount":null,"realCount":2}]