[{"hno":15182,"hnm":"이도주공2,3단지","typeNm":"아파트","callPrice":"3853.79","realPrice":"3994.59","kbPrice":3652.21,"call_KB":"105.51","real_KB":"109.37","callCount":22,"realCount":1,"naver_link":"https://new.land.naver.com/complexes/15182"},{"hno":17170,"hnm":"주공1단지","typeNm":"재건축","callPrice":"3801.73","realPrice":"3500.57","kbPrice":3479.99,"call_KB":"109.24","real_KB":"100.59","callCount":14,"realCount":9,"naver_link":"https://new.land.naver.com/complexes/17170"},{"hno":106265,"hnm":"제주이도한일베라체","typeNm":"아파트","callPrice":"2272.59","realPrice":"2083.94","kbPrice":2029.93,"call_KB":"111.95","real_KB":"102.66","callCount":13,"realCount":6,"naver_link":"https://new.land.naver.com/complexes/106265"},{"hno":17169,"hnm":"영산홍","typeNm":"아파트","callPrice":"1580.65","realPrice":"없음","kbPrice":1378.71,"call_KB":"114.64","real_KB":"없음","callCount":3,"realCount":0,"naver_link":"https://new.land.naver.com/complexes/17169"},{"hno":15178,"hnm":"동아","typeNm":"아파트","callPrice":"0.00","realPrice":"1018.84","kbPrice":987.97,"call_KB":"0.00","real_KB":"103.12","callCount":0,"realCount":1,"naver_link":"https://new.land.naver.com/complexes/15178"}]