[{"hno":5905,"hnm":"한라","typeNm":"아파트","callPrice":"779.14","realPrice":"709.35","kbPrice":715.92,"call_KB":"108.83","real_KB":"99.08","callCount":33,"realCount":12,"naver_link":"https://new.land.naver.com/complexes/5905"},{"hno":5879,"hnm":"남산삼익","typeNm":"아파트","callPrice":"619.72","realPrice":"546.73","kbPrice":575.56,"call_KB":"107.67","real_KB":"94.99","callCount":7,"realCount":4,"naver_link":"https://new.land.naver.com/complexes/5879"},{"hno":5890,"hnm":"삼익타워맨션","typeNm":"아파트","callPrice":"571.82","realPrice":"239.26","kbPrice":422.66,"call_KB":"135.28","real_KB":"56.60","callCount":12,"realCount":-1,"naver_link":"https://new.land.naver.com/complexes/5890"},{"hno":5910,"hnm":"내곡현대","typeNm":"아파트","callPrice":"420.57","realPrice":"814.64","kbPrice":787.92,"call_KB":"53.37","real_KB":"103.39","callCount":9,"realCount":8,"naver_link":"https://new.land.naver.com/complexes/5910"}]